git_status_cli/__init__.py
git_status_cli/cli.py
git_status_cli/config.yaml
git_status_cli-1.3.0.dist-info/entry_points.txt
git_status_cli-1.3.0.dist-info/LICENSE.txt
git_status_cli-1.3.0.dist-info/WHEEL
git_status_cli-1.3.0.dist-info/METADATA
git_status_cli-1.3.0.dist-info/RECORD
